{
  "fetched_at": "2026-04-06T12:57:57.165710+00:00",
  "fetched_at_ist": "2026-04-06 18:28 IST",
  "coverage": {
    "nse_stocks_fetched": 85,
    "nse_stocks_attempted": 93,
    "indices_fetched": 3,
    "commodities_fetched": 5,
    "portfolio_stocks_with_pnl": 33
  },
  "indices": {
    "NIFTY_50": {
      "price": 22968.25,
      "prev_close": 22713.1,
      "change": 255.15,
      "change_pct": 1.12,
      "volume": 0,
      "ticker": "^NSEI"
    },
    "SENSEX": {
      "price": 74106.85,
      "prev_close": 73319.55,
      "change": 787.3,
      "change_pct": 1.07,
      "volume": 0,
      "ticker": "^BSESN"
    },
    "BANKNIFTY": {
      "price": 52609.1,
      "prev_close": 51548.75,
      "change": 1060.35,
      "change_pct": 2.06,
      "volume": 0,
      "ticker": "^NSEBANK"
    }
  },
  "commodities": {
    "GOLD_USD": {
      "price": 4704.0,
      "prev_close": 4704.0,
      "change": 0.0,
      "change_pct": 0.0,
      "volume": 50890,
      "ticker": "GC=F"
    },
    "SILVER_USD": {
      "price": 73.49,
      "prev_close": 73.49,
      "change": 0.0,
      "change_pct": 0.0,
      "volume": 9435,
      "ticker": "SI=F"
    },
    "CRUDE_WTI": {
      "price": 110.38,
      "prev_close": 110.38,
      "change": 0.0,
      "change_pct": 0.0,
      "volume": 98860,
      "ticker": "CL=F"
    },
    "BRENT_CRUDE": {
      "price": 108.38,
      "prev_close": 108.38,
      "change": 0.0,
      "change_pct": 0.0,
      "volume": 13531,
      "ticker": "BZ=F"
    },
    "NAT_GAS": {
      "price": 2.83,
      "prev_close": 2.83,
      "change": 0.0,
      "change_pct": 0.0,
      "volume": 25644,
      "ticker": "NG=F"
    }
  },
  "portfolio": {
    "CDSL": {
      "price": 1205.3,
      "prev_close": 1186.3,
      "change": 19.0,
      "change_pct": 1.6,
      "volume": 2142548,
      "symbol": "CDSL",
      "yahoo_ticker": "CDSL.NS",
      "broker": "ICICI",
      "avg_buy": 1184.8,
      "qty": 64,
      "invested": 75827.2,
      "market_value": 77139.2,
      "pnl": 1312.0,
      "pnl_pct": 1.73
    },
    "COCHINSHIP": {
      "price": 1333.9,
      "prev_close": 1314.5,
      "change": 19.4,
      "change_pct": 1.48,
      "volume": 1734066,
      "symbol": "COCHINSHIP",
      "yahoo_ticker": "COCHINSHIP.NS",
      "broker": "ICICI",
      "avg_buy": 1384.09,
      "qty": 90,
      "invested": 124568.1,
      "market_value": 120051.0,
      "pnl": -4517.1,
      "pnl_pct": -3.63
    },
    "GODREJPROP": {
      "price": 1584.7,
      "prev_close": 1508.3,
      "change": 76.4,
      "change_pct": 5.07,
      "volume": 2222698,
      "symbol": "GODREJPROP",
      "yahoo_ticker": "GODREJPROP.NS",
      "broker": "ICICI",
      "avg_buy": 1611.67,
      "qty": 68,
      "invested": 109593.56,
      "market_value": 107759.6,
      "pnl": -1833.96,
      "pnl_pct": -1.67
    },
    "IGIL": {
      "price": 322.05,
      "prev_close": 320.35,
      "change": 1.7,
      "change_pct": 0.53,
      "volume": 290058,
      "symbol": "IGIL",
      "yahoo_ticker": "IGIL.NS",
      "broker": "ICICI",
      "avg_buy": 327.31,
      "qty": 150,
      "invested": 49096.5,
      "market_value": 48307.5,
      "pnl": -789.0,
      "pnl_pct": -1.61
    },
    "INDIGO": {
      "price": 4312.5,
      "prev_close": 4193.5,
      "change": 119.0,
      "change_pct": 2.84,
      "volume": 1802238,
      "symbol": "INDIGO",
      "yahoo_ticker": "INDIGO.NS",
      "broker": "ICICI",
      "avg_buy": 4204.69,
      "qty": 19,
      "invested": 79889.11,
      "market_value": 81937.5,
      "pnl": 2048.39,
      "pnl_pct": 2.56
    },
    "IRCON": {
      "price": 125.94,
      "prev_close": 124.96,
      "change": 0.98,
      "change_pct": 0.78,
      "volume": 3978507,
      "symbol": "IRCON",
      "yahoo_ticker": "IRCON.NS",
      "broker": "ICICI",
      "avg_buy": 120.97,
      "qty": 420,
      "invested": 50807.4,
      "market_value": 52894.8,
      "pnl": 2087.4,
      "pnl_pct": 4.11
    },
    "IREDA": {
      "price": 115.58,
      "prev_close": 114.94,
      "change": 0.64,
      "change_pct": 0.56,
      "volume": 8846812,
      "symbol": "IREDA",
      "yahoo_ticker": "IREDA.NS",
      "broker": "ICICI",
      "avg_buy": 114.57,
      "qty": 400,
      "invested": 45828.0,
      "market_value": 46232.0,
      "pnl": 404.0,
      "pnl_pct": 0.88
    },
    "ITC": {
      "price": 294.85,
      "prev_close": 292.85,
      "change": 2.0,
      "change_pct": 0.68,
      "volume": 18042168,
      "symbol": "ITC",
      "yahoo_ticker": "ITC.NS",
      "broker": "ICICI",
      "avg_buy": 301.96,
      "qty": 520,
      "invested": 157019.2,
      "market_value": 153322.0,
      "pnl": -3697.2,
      "pnl_pct": -2.35
    },
    "JIOFIN": {
      "price": 235.31,
      "prev_close": 229.48,
      "change": 5.83,
      "change_pct": 2.54,
      "volume": 16031408,
      "symbol": "JIOFIN",
      "yahoo_ticker": "JIOFIN.NS",
      "broker": "ICICI",
      "avg_buy": 234.99,
      "qty": 220,
      "invested": 51697.8,
      "market_value": 51768.2,
      "pnl": 70.4,
      "pnl_pct": 0.14
    },
    "MAZDOCK": {
      "price": 2313.7,
      "prev_close": 2264.6,
      "change": 49.1,
      "change_pct": 2.17,
      "volume": 2127359,
      "symbol": "MAZDOCK",
      "yahoo_ticker": "MAZDOCK.NS",
      "broker": "ICICI",
      "avg_buy": 2316.75,
      "qty": 20,
      "invested": 46335.0,
      "market_value": 46274.0,
      "pnl": -61.0,
      "pnl_pct": -0.13
    },
    "MRPL": {
      "price": 178.94,
      "prev_close": 182.14,
      "change": -3.2,
      "change_pct": -1.76,
      "volume": 5822849,
      "symbol": "MRPL",
      "yahoo_ticker": "MRPL.NS",
      "broker": "ICICI",
      "avg_buy": 196.4,
      "qty": 300,
      "invested": 58920.0,
      "market_value": 53682.0,
      "pnl": -5238.0,
      "pnl_pct": -8.89
    },
    "NCC": {
      "price": 141.84,
      "prev_close": 141.71,
      "change": 0.13,
      "change_pct": 0.09,
      "volume": 2822482,
      "symbol": "NCC",
      "yahoo_ticker": "NCC.NS",
      "broker": "ICICI",
      "avg_buy": 142.64,
      "qty": 180,
      "invested": 25675.2,
      "market_value": 25531.2,
      "pnl": -144.0,
      "pnl_pct": -0.56
    },
    "PREMEXPLN": {
      "price": 429.9,
      "prev_close": 425.7,
      "change": 4.2,
      "change_pct": 0.99,
      "volume": 287263,
      "symbol": "PREMEXPLN",
      "yahoo_ticker": "PREMEXPLN.NS",
      "broker": "ICICI",
      "avg_buy": 436.53,
      "qty": 150,
      "invested": 65479.5,
      "market_value": 64485.0,
      "pnl": -994.5,
      "pnl_pct": -1.52
    },
    "SBISILVER": {
      "price": 227.86,
      "prev_close": 221.41,
      "change": 6.45,
      "change_pct": 2.91,
      "volume": 1874577,
      "symbol": "SBISILVER",
      "yahoo_ticker": "SBISILVER.NS",
      "broker": "ICICI",
      "avg_buy": 225.05,
      "qty": 730,
      "invested": 164286.5,
      "market_value": 166337.8,
      "pnl": 2051.3,
      "pnl_pct": 1.25
    },
    "SETFGOLD": {
      "price": 126.71,
      "prev_close": 124.32,
      "change": 2.39,
      "change_pct": 1.92,
      "volume": 12531556,
      "symbol": "SETFGOLD",
      "yahoo_ticker": "SETFGOLD.NS",
      "broker": "ICICI",
      "avg_buy": 125.21,
      "qty": 1190,
      "invested": 148999.9,
      "market_value": 150784.9,
      "pnl": 1785.0,
      "pnl_pct": 1.2
    },
    "SUZLON": {
      "price": 41.59,
      "prev_close": 40.78,
      "change": 0.81,
      "change_pct": 1.99,
      "volume": 66616433,
      "symbol": "SUZLON",
      "yahoo_ticker": "SUZLON.NS",
      "broker": "ICICI",
      "avg_buy": 40.55,
      "qty": 2000,
      "invested": 81100.0,
      "market_value": 83180.0,
      "pnl": 2080.0,
      "pnl_pct": 2.56
    },
    "SWIGGY": {
      "price": 271.8,
      "prev_close": 275.35,
      "change": -3.55,
      "change_pct": -1.29,
      "volume": 20125302,
      "symbol": "SWIGGY",
      "yahoo_ticker": "SWIGGY.NS",
      "broker": "ICICI",
      "avg_buy": 298.75,
      "qty": 170,
      "invested": 50787.5,
      "market_value": 46206.0,
      "pnl": -4581.5,
      "pnl_pct": -9.02
    },
    "URBANCO": {
      "price": 123.4,
      "prev_close": 121.8,
      "change": 1.6,
      "change_pct": 1.31,
      "volume": 3340409,
      "symbol": "URBANCO",
      "yahoo_ticker": "URBANCO.NS",
      "broker": "ICICI",
      "avg_buy": 122.1,
      "qty": 725,
      "invested": 88522.5,
      "market_value": 89465.0,
      "pnl": 942.5,
      "pnl_pct": 1.06
    },
    "ACME SOLAR": {
      "price": 280.25,
      "prev_close": 274.65,
      "change": 5.6,
      "change_pct": 2.04,
      "volume": 2379714,
      "symbol": "ACME SOLAR",
      "yahoo_ticker": "ACMESOLAR.NS",
      "broker": "Groww",
      "avg_buy": 289.0,
      "qty": 51,
      "invested": 14739.0,
      "market_value": 14292.75,
      "pnl": -446.25,
      "pnl_pct": -3.03
    },
    "ADANI PORT": {
      "price": 1387.1,
      "prev_close": 1377.6,
      "change": 9.5,
      "change_pct": 0.69,
      "volume": 2519187,
      "symbol": "ADANI PORT",
      "yahoo_ticker": "ADANIPORTS.NS",
      "broker": "Groww",
      "avg_buy": 1579.0,
      "qty": 100,
      "invested": 157900.0,
      "market_value": 138710.0,
      "pnl": -19190.0,
      "pnl_pct": -12.15
    },
    "ADANI POWER": {
      "price": 163.26,
      "prev_close": 159.97,
      "change": 3.29,
      "change_pct": 2.06,
      "volume": 127453734,
      "symbol": "ADANI POWER",
      "yahoo_ticker": "ADANIPOWER.NS",
      "broker": "Groww",
      "avg_buy": 157.14,
      "qty": 1245,
      "invested": 195639.3,
      "market_value": 203258.7,
      "pnl": 7619.4,
      "pnl_pct": 3.89
    },
    "ASTRA MICRO": {
      "price": 943.95,
      "prev_close": 952.65,
      "change": -8.7,
      "change_pct": -0.91,
      "volume": 474138,
      "symbol": "ASTRA MICRO",
      "yahoo_ticker": "ASTRAMICRO.NS",
      "broker": "Groww",
      "avg_buy": 562.35,
      "qty": 20,
      "invested": 11247.0,
      "market_value": 18879.0,
      "pnl": 7632.0,
      "pnl_pct": 67.86
    },
    "COAL INDIA": {
      "price": 459.55,
      "prev_close": 449.35,
      "change": 10.2,
      "change_pct": 2.27,
      "volume": 12401827,
      "symbol": "COAL INDIA",
      "yahoo_ticker": "COALINDIA.NS",
      "broker": "Groww",
      "avg_buy": 345.55,
      "qty": 55,
      "invested": 19005.25,
      "market_value": 25275.25,
      "pnl": 6270.0,
      "pnl_pct": 32.99
    },
    "IRFC": {
      "price": 92.72,
      "prev_close": 91.84,
      "change": 0.88,
      "change_pct": 0.96,
      "volume": 17303853,
      "symbol": "IRFC",
      "yahoo_ticker": "IRFC.NS",
      "broker": "Groww",
      "avg_buy": 130.01,
      "qty": 200,
      "invested": 26002.0,
      "market_value": 18544.0,
      "pnl": -7458.0,
      "pnl_pct": -28.68
    },
    "IREDA (Groww)": {
      "price": 115.58,
      "prev_close": 114.94,
      "change": 0.64,
      "change_pct": 0.56,
      "volume": 8846812,
      "symbol": "IREDA (Groww)",
      "yahoo_ticker": "IREDA.NS",
      "broker": "Groww",
      "avg_buy": 175.0,
      "qty": 200,
      "invested": 35000.0,
      "market_value": 23116.0,
      "pnl": -11884.0,
      "pnl_pct": -33.95
    },
    "IGIL (Groww)": {
      "price": 322.05,
      "prev_close": 320.35,
      "change": 1.7,
      "change_pct": 0.53,
      "volume": 290058,
      "symbol": "IGIL (Groww)",
      "yahoo_ticker": "IGIL.NS",
      "broker": "Groww",
      "avg_buy": 372.0,
      "qty": 60,
      "invested": 22320.0,
      "market_value": 19323.0,
      "pnl": -2997.0,
      "pnl_pct": -13.43
    },
    "IRCON (Groww)": {
      "price": 125.94,
      "prev_close": 124.96,
      "change": 0.98,
      "change_pct": 0.78,
      "volume": 3978507,
      "symbol": "IRCON (Groww)",
      "yahoo_ticker": "IRCON.NS",
      "broker": "Groww",
      "avg_buy": 162.07,
      "qty": 350,
      "invested": 56724.5,
      "market_value": 44079.0,
      "pnl": -12645.5,
      "pnl_pct": -22.29
    },
    "JIOFIN (Groww)": {
      "price": 235.31,
      "prev_close": 229.48,
      "change": 5.83,
      "change_pct": 2.54,
      "volume": 16031408,
      "symbol": "JIOFIN (Groww)",
      "yahoo_ticker": "JIOFIN.NS",
      "broker": "Groww",
      "avg_buy": 238.3,
      "qty": 300,
      "invested": 71490.0,
      "market_value": 70593.0,
      "pnl": -897.0,
      "pnl_pct": -1.25
    },
    "NHPC": {
      "price": 76.16,
      "prev_close": 75.33,
      "change": 0.83,
      "change_pct": 1.1,
      "volume": 8012437,
      "symbol": "NHPC",
      "yahoo_ticker": "NHPC.NS",
      "broker": "Groww",
      "avg_buy": 104.28,
      "qty": 400,
      "invested": 41712.0,
      "market_value": 30464.0,
      "pnl": -11248.0,
      "pnl_pct": -26.97
    },
    "PI INDUSTRIES": {
      "price": 2837.7,
      "prev_close": 2797.2,
      "change": 40.5,
      "change_pct": 1.45,
      "volume": 191728,
      "symbol": "PI INDUSTRIES",
      "yahoo_ticker": "PIIND.NS",
      "broker": "Groww",
      "avg_buy": 3877.5,
      "qty": 6,
      "invested": 23265.0,
      "market_value": 17026.2,
      "pnl": -6238.8,
      "pnl_pct": -26.82
    },
    "RELIANCE": {
      "price": 1304.7,
      "prev_close": 1350.5,
      "change": -45.8,
      "change_pct": -3.39,
      "volume": 29269942,
      "symbol": "RELIANCE",
      "yahoo_ticker": "RELIANCE.NS",
      "broker": "Groww",
      "avg_buy": 1399.1,
      "qty": 36,
      "invested": 50367.6,
      "market_value": 46969.2,
      "pnl": -3398.4,
      "pnl_pct": -6.75
    },
    "SUZLON (Groww)": {
      "price": 41.59,
      "prev_close": 40.78,
      "change": 0.81,
      "change_pct": 1.99,
      "volume": 66616433,
      "symbol": "SUZLON (Groww)",
      "yahoo_ticker": "SUZLON.NS",
      "broker": "Groww",
      "avg_buy": 49.13,
      "qty": 600,
      "invested": 29478.0,
      "market_value": 24954.0,
      "pnl": -4524.0,
      "pnl_pct": -15.35
    },
    "SWIGGY (Groww)": {
      "price": 271.8,
      "prev_close": 275.35,
      "change": -3.55,
      "change_pct": -1.29,
      "volume": 20125302,
      "symbol": "SWIGGY (Groww)",
      "yahoo_ticker": "SWIGGY.NS",
      "broker": "Groww",
      "avg_buy": 375.28,
      "qty": 212,
      "invested": 79559.36,
      "market_value": 57621.6,
      "pnl": -21937.76,
      "pnl_pct": -27.57
    }
  },
  "nse_universe": {
    "RELIANCE.NS": {
      "price": 1304.7,
      "prev_close": 1350.5,
      "change": -45.8,
      "change_pct": -3.39,
      "volume": 29269942
    },
    "TCS.NS": {
      "price": 2473.9,
      "prev_close": 2450.7,
      "change": 23.2,
      "change_pct": 0.95,
      "volume": 2571726
    },
    "HDFCBANK.NS": {
      "price": 771.0,
      "prev_close": 750.9,
      "change": 20.1,
      "change_pct": 2.68,
      "volume": 42969196
    },
    "ICICIBANK.NS": {
      "price": 1231.4,
      "prev_close": 1215.8,
      "change": 15.6,
      "change_pct": 1.28,
      "volume": 10057526
    },
    "BHARTIARTL.NS": {
      "price": 1792.8,
      "prev_close": 1789.7,
      "change": 3.1,
      "change_pct": 0.17,
      "volume": 8183288
    },
    "SBIN.NS": {
      "price": 1032.75,
      "prev_close": 1018.4,
      "change": 14.35,
      "change_pct": 1.41,
      "volume": 23573719
    },
    "KOTAKBANK.NS": {
      "price": 360.55,
      "prev_close": 358.0,
      "change": 2.55,
      "change_pct": 0.71,
      "volume": 18317857
    },
    "INFY.NS": {
      "price": 1306.2,
      "prev_close": 1300.8,
      "change": 5.4,
      "change_pct": 0.42,
      "volume": 10207521
    },
    "LT.NS": {
      "price": 3727.7,
      "prev_close": 3613.1,
      "change": 114.6,
      "change_pct": 3.17,
      "volume": 3352882
    },
    "HCLTECH.NS": {
      "price": 1403.3,
      "prev_close": 1402.2,
      "change": 1.1,
      "change_pct": 0.08,
      "volume": 2133970
    },
    "MARUTI.NS": {
      "price": 12688.0,
      "prev_close": 12631.0,
      "change": 57.0,
      "change_pct": 0.45,
      "volume": 382632
    },
    "AXISBANK.NS": {
      "price": 1245.3,
      "prev_close": 1197.9,
      "change": 47.4,
      "change_pct": 3.96,
      "volume": 7846939
    },
    "BAJFINANCE.NS": {
      "price": 850.85,
      "prev_close": 826.85,
      "change": 24.0,
      "change_pct": 2.9,
      "volume": 12503823
    },
    "TITAN.NS": {
      "price": 4246.1,
      "prev_close": 4097.2,
      "change": 148.9,
      "change_pct": 3.63,
      "volume": 1678149
    },
    "SUNPHARMA.NS": {
      "price": 1694.6,
      "prev_close": 1693.6,
      "change": 1.0,
      "change_pct": 0.06,
      "volume": 3533645
    },
    "ASIANPAINT.NS": {
      "price": 2184.3,
      "prev_close": 2169.0,
      "change": 15.3,
      "change_pct": 0.71,
      "volume": 2048186
    },
    "NTPC.NS": {
      "price": 366.1,
      "prev_close": 359.65,
      "change": 6.45,
      "change_pct": 1.79,
      "volume": 11532594
    },
    "POWERGRID.NS": {
      "price": 295.15,
      "prev_close": 289.95,
      "change": 5.2,
      "change_pct": 1.79,
      "volume": 9290344
    },
    "ULTRACEMCO.NS": {
      "price": 10955.0,
      "prev_close": 10620.0,
      "change": 335.0,
      "change_pct": 3.15,
      "volume": 374401
    },
    "ONGC.NS": {
      "price": 281.85,
      "prev_close": 287.2,
      "change": -5.35,
      "change_pct": -1.86,
      "volume": 24434694
    },
    "WIPRO.NS": {
      "price": 197.29,
      "prev_close": 194.91,
      "change": 2.38,
      "change_pct": 1.22,
      "volume": 23277703
    },
    "HINDALCO.NS": {
      "price": 927.45,
      "prev_close": 916.25,
      "change": 11.2,
      "change_pct": 1.22,
      "volume": 5555262
    },
    "JSWSTEEL.NS": {
      "price": 1133.6,
      "prev_close": 1141.3,
      "change": -7.7,
      "change_pct": -0.67,
      "volume": 3213587
    },
    "TECHM.NS": {
      "price": 1449.5,
      "prev_close": 1441.5,
      "change": 8.0,
      "change_pct": 0.55,
      "volume": 1476608
    },
    "GRASIM.NS": {
      "price": 2614.4,
      "prev_close": 2564.1,
      "change": 50.3,
      "change_pct": 1.96,
      "volume": 720323
    },
    "INDUSINDBK.NS": {
      "price": 786.2,
      "prev_close": 778.7,
      "change": 7.5,
      "change_pct": 0.96,
      "volume": 2512028
    },
    "TATACONSUM.NS": {
      "price": 1055.2,
      "prev_close": 1042.0,
      "change": 13.2,
      "change_pct": 1.27,
      "volume": 2178739
    },
    "BAJAJFINSV.NS": {
      "price": 1672.3,
      "prev_close": 1640.7,
      "change": 31.6,
      "change_pct": 1.93,
      "volume": 1215027
    },
    "CIPLA.NS": {
      "price": 1200.9,
      "prev_close": 1192.4,
      "change": 8.5,
      "change_pct": 0.71,
      "volume": 2188579
    },
    "DRREDDY.NS": {
      "price": 1217.8,
      "prev_close": 1217.3,
      "change": 0.5,
      "change_pct": 0.04,
      "volume": 1099287
    },
    "NESTLEIND.NS": {
      "price": 1216.0,
      "prev_close": 1191.3,
      "change": 24.7,
      "change_pct": 2.07,
      "volume": 1460934
    },
    "DIVISLAB.NS": {
      "price": 5821.0,
      "prev_close": 5856.5,
      "change": -35.5,
      "change_pct": -0.61,
      "volume": 346182
    },
    "BRITANNIA.NS": {
      "price": 5535.0,
      "prev_close": 5442.0,
      "change": 93.0,
      "change_pct": 1.71,
      "volume": 228271
    },
    "BPCL.NS": {
      "price": 278.7,
      "prev_close": 278.15,
      "change": 0.55,
      "change_pct": 0.2,
      "volume": 11919597
    },
    "COALINDIA.NS": {
      "price": 459.55,
      "prev_close": 449.35,
      "change": 10.2,
      "change_pct": 2.27,
      "volume": 12401827
    },
    "SHRIRAMFIN.NS": {
      "price": 928.0,
      "prev_close": 891.6,
      "change": 36.4,
      "change_pct": 4.08,
      "volume": 5896091
    },
    "HDFCLIFE.NS": {
      "price": 580.4,
      "prev_close": 566.1,
      "change": 14.3,
      "change_pct": 2.53,
      "volume": 4333517
    },
    "SBILIFE.NS": {
      "price": 1836.8,
      "prev_close": 1774.0,
      "change": 62.8,
      "change_pct": 3.54,
      "volume": 1720983
    },
    "EICHERMOT.NS": {
      "price": 6596.0,
      "prev_close": 6649.5,
      "change": -53.5,
      "change_pct": -0.8,
      "volume": 970861
    },
    "ADANIENT.NS": {
      "price": 1902.2,
      "prev_close": 1834.2,
      "change": 68.0,
      "change_pct": 3.71,
      "volume": 3153236
    },
    "ADANIPORTS.NS": {
      "price": 1387.1,
      "prev_close": 1377.6,
      "change": 9.5,
      "change_pct": 0.69,
      "volume": 2519187
    },
    "HEROMOTOCO.NS": {
      "price": 5103.5,
      "prev_close": 5011.5,
      "change": 92.0,
      "change_pct": 1.84,
      "volume": 348531
    },
    "APOLLOHOSP.NS": {
      "price": 7373.0,
      "prev_close": 7317.5,
      "change": 55.5,
      "change_pct": 0.76,
      "volume": 360084
    },
    "BAJAJ-AUTO.NS": {
      "price": 8942.5,
      "prev_close": 8758.5,
      "change": 184.0,
      "change_pct": 2.1,
      "volume": 313790
    },
    "M&M.NS": {
      "price": 3021.6,
      "prev_close": 3011.7,
      "change": 9.9,
      "change_pct": 0.33,
      "volume": 2554721
    },
    "TATASTEEL.NS": {
      "price": 196.1,
      "prev_close": 194.14,
      "change": 1.96,
      "change_pct": 1.01,
      "volume": 28097933
    },
    "TRENT.NS": {
      "price": 3833.6,
      "prev_close": 3550.6,
      "change": 283.0,
      "change_pct": 7.97,
      "volume": 4877363
    },
    "BEL.NS": {
      "price": 427.15,
      "prev_close": 421.6,
      "change": 5.55,
      "change_pct": 1.32,
      "volume": 12326050
    },
    "JIOFIN.NS": {
      "price": 235.31,
      "prev_close": 229.48,
      "change": 5.83,
      "change_pct": 2.54,
      "volume": 16031408
    },
    "IREDA.NS": {
      "price": 115.58,
      "prev_close": 114.94,
      "change": 0.64,
      "change_pct": 0.56,
      "volume": 8846812
    },
    "IRFC.NS": {
      "price": 92.72,
      "prev_close": 91.84,
      "change": 0.88,
      "change_pct": 0.96,
      "volume": 17303853
    },
    "IRCON.NS": {
      "price": 125.94,
      "prev_close": 124.96,
      "change": 0.98,
      "change_pct": 0.78,
      "volume": 3978507
    },
    "NCC.NS": {
      "price": 141.84,
      "prev_close": 141.71,
      "change": 0.13,
      "change_pct": 0.09,
      "volume": 2822482
    },
    "CDSL.NS": {
      "price": 1205.3,
      "prev_close": 1186.3,
      "change": 19.0,
      "change_pct": 1.6,
      "volume": 2142548
    },
    "SUZLON.NS": {
      "price": 41.59,
      "prev_close": 40.78,
      "change": 0.81,
      "change_pct": 1.99,
      "volume": 66616433
    },
    "SWIGGY.NS": {
      "price": 271.8,
      "prev_close": 275.35,
      "change": -3.55,
      "change_pct": -1.29,
      "volume": 20125302
    },
    "NYKAA.NS": {
      "price": 252.52,
      "prev_close": 245.98,
      "change": 6.54,
      "change_pct": 2.66,
      "volume": 10402457
    },
    "DMART.NS": {
      "price": 4551.3,
      "prev_close": 4362.4,
      "change": 188.9,
      "change_pct": 4.33,
      "volume": 1915208
    },
    "INDIGO.NS": {
      "price": 4312.5,
      "prev_close": 4193.5,
      "change": 119.0,
      "change_pct": 2.84,
      "volume": 1802238
    },
    "COCHINSHIP.NS": {
      "price": 1333.9,
      "prev_close": 1314.5,
      "change": 19.4,
      "change_pct": 1.48,
      "volume": 1734066
    },
    "MAZDOCK.NS": {
      "price": 2313.7,
      "prev_close": 2264.6,
      "change": 49.1,
      "change_pct": 2.17,
      "volume": 2127359
    },
    "GRSE.NS": {
      "price": 2259.5,
      "prev_close": 2255.3,
      "change": 4.2,
      "change_pct": 0.19,
      "volume": 2895430
    },
    "GODREJPROP.NS": {
      "price": 1584.7,
      "prev_close": 1508.3,
      "change": 76.4,
      "change_pct": 5.07,
      "volume": 2222698
    },
    "PRESTIGE.NS": {
      "price": 1183.2,
      "prev_close": 1152.0,
      "change": 31.2,
      "change_pct": 2.71,
      "volume": 2407289
    },
    "SOBHA.NS": {
      "price": 1220.0,
      "prev_close": 1156.8,
      "change": 63.2,
      "change_pct": 5.46,
      "volume": 214185
    },
    "OBEROIRLTY.NS": {
      "price": 1519.9,
      "prev_close": 1506.9,
      "change": 13.0,
      "change_pct": 0.86,
      "volume": 288482
    },
    "MRPL.NS": {
      "price": 178.94,
      "prev_close": 182.14,
      "change": -3.2,
      "change_pct": -1.76,
      "volume": 5822849
    },
    "GAIL.NS": {
      "price": 143.14,
      "prev_close": 141.73,
      "change": 1.41,
      "change_pct": 0.99,
      "volume": 11466059
    },
    "IOC.NS": {
      "price": 134.05,
      "prev_close": 134.13,
      "change": -0.08,
      "change_pct": -0.06,
      "volume": 25349716
    },
    "HINDPETRO.NS": {
      "price": 328.05,
      "prev_close": 326.0,
      "change": 2.05,
      "change_pct": 0.63,
      "volume": 5087562
    },
    "ACMESOLAR.NS": {
      "price": 280.25,
      "prev_close": 274.65,
      "change": 5.6,
      "change_pct": 2.04,
      "volume": 2379714
    },
    "ADANIGREEN.NS": {
      "price": 921.1,
      "prev_close": 856.0,
      "change": 65.1,
      "change_pct": 7.61,
      "volume": 13111794
    },
    "ADANIPOWER.NS": {
      "price": 163.26,
      "prev_close": 159.97,
      "change": 3.29,
      "change_pct": 2.06,
      "volume": 127453734
    },
    "TATAPOWER.NS": {
      "price": 383.85,
      "prev_close": 385.0,
      "change": -1.15,
      "change_pct": -0.3,
      "volume": 6688463
    },
    "NHPC.NS": {
      "price": 76.16,
      "prev_close": 75.33,
      "change": 0.83,
      "change_pct": 1.1,
      "volume": 8012437
    },
    "PREMEXPLN.NS": {
      "price": 429.9,
      "prev_close": 425.7,
      "change": 4.2,
      "change_pct": 0.99,
      "volume": 287263
    },
    "URBANCO.NS": {
      "price": 123.4,
      "prev_close": 121.8,
      "change": 1.6,
      "change_pct": 1.31,
      "volume": 3340409
    },
    "IGIL.NS": {
      "price": 322.05,
      "prev_close": 320.35,
      "change": 1.7,
      "change_pct": 0.53,
      "volume": 290058
    },
    "ASTRAMICRO.NS": {
      "price": 943.95,
      "prev_close": 952.65,
      "change": -8.7,
      "change_pct": -0.91,
      "volume": 474138
    },
    "SBISILVER.NS": {
      "price": 227.86,
      "prev_close": 221.41,
      "change": 6.45,
      "change_pct": 2.91,
      "volume": 1874577
    },
    "SETFGOLD.NS": {
      "price": 126.71,
      "prev_close": 124.32,
      "change": 2.39,
      "change_pct": 1.92,
      "volume": 12531556
    },
    "ITC.NS": {
      "price": 294.85,
      "prev_close": 292.85,
      "change": 2.0,
      "change_pct": 0.68,
      "volume": 18042168
    },
    "PIIND.NS": {
      "price": 2837.7,
      "prev_close": 2797.2,
      "change": 40.5,
      "change_pct": 1.45,
      "volume": 191728
    },
    "GOLDBEES.NS": {
      "price": 122.81,
      "prev_close": 120.58,
      "change": 2.23,
      "change_pct": 1.85,
      "volume": 42268167
    },
    "SILVERBEES.NS": {
      "price": 222.38,
      "prev_close": 215.95,
      "change": 6.43,
      "change_pct": 2.98,
      "volume": 42803413
    }
  }
}